LICENSE
MANIFEST.in
README.md
setup.py
spider/README.md
spider/__init__.py
spider/_misc.py
spider/_virtual_import.py
spider/param.py
spider/teaser.py
spider/elements/_poly_calc.c
spider/constraints/ConstraintCollection.py
spider/constraints/__init__.py
spider/constraints/constraint_checker/BaseConstraintChecker.py
spider/constraints/constraint_checker/CartConstraintChecker.py
spider/constraints/constraint_checker/ControlConstraintChecker.py
spider/constraints/constraint_checker/FrenetConstraintChecker.py
spider/constraints/constraint_checker/__init__.py
spider/constraints/constraint_formulator/__init__.py
spider/control/IDMController.py
spider/control/SimpleController.py
spider/control/__init__.py
spider/control/lateral/PurePursuitController.py
spider/control/lateral/__init__.py
spider/control/longitudinal/IDMLonController.py
spider/control/longitudinal/PIDLonController.py
spider/control/longitudinal/__init__.py
spider/control/vehicle_model/__init__.py
spider/control/vehicle_model/bicycle.py
spider/data/DataBuffer.py
spider/data/Dataset.py
spider/data/__init__.py
spider/data/common.py
spider/data/data_factory.py
spider/data/decorators.py
spider/elements/__init__.py
spider/elements/_poly_calc.pyx
spider/elements/box.py
spider/elements/curves.py
spider/elements/graph.py
spider/elements/grid.py
spider/elements/map.py
spider/elements/trajectory.py
spider/elements/vehicle.py
spider/evaluator/CostEvaluator.py
spider/evaluator/__init__.py
spider/interface/BaseBenchmark.py
spider/interface/BaseInterface.py
spider/interface/__init__.py
spider/interface/metrics_collection.py
spider/interface/carla/CarlaInterface.py
spider/interface/carla/__init__.py
spider/interface/carla/_control_utils.py
spider/interface/carla/_light_utils.py
spider/interface/carla/_route_utils.py
spider/interface/carla/_weather_utils.py
spider/interface/carla/common.py
spider/interface/carla/presets.py
spider/interface/carla/visualize.py
spider/interface/highway_env/HighwayEnvBenchmark.py
spider_python.egg-info/PKG-INFO
spider_python.egg-info/SOURCES.txt
spider_python.egg-info/dependency_links.txt
spider_python.egg-info/requires.txt
spider_python.egg-info/top_level.txt