Metadata-Version: 2.1
Name: spider-python
Version: 0.1.16.5
Summary: SPIDER -- Self-driving Planning and Intelligent Decision-making Engine with Reinforcement learning
Home-page: https://github.com/ZelinQian/SPIDER
Author: Zelin Qian
Author-email: qzl22@mails.tsinghua.edu.cn
License: MIT
Platform: UNKNOWN
Provides-Extra: opencv-python
